[
  {
    "path": "Format lampiran penilaian/Salinan 01. Format Penilaian Antar teman 2 Jawaban.docx",
    "size": 4539,
    "name": "Salinan 01. Format Penilaian Antar teman 2 Jawaban.docx"
  },
  {
    "path": "Format lampiran penilaian/Salinan 03. Format Penilaian Antar teman Empat Jawaban.docx",
    "size": 4728,
    "name": "Salinan 03. Format Penilaian Antar teman Empat Jawaban.docx"
  },
  {
    "path": "Format lampiran penilaian/Salinan 03. Instrumen Penilaian Tes Lisan.docx",
    "size": 7040,
    "name": "Salinan 03. Instrumen Penilaian Tes Lisan.docx"
  },
  {
    "path": "Format lampiran penilaian/Salinan 04. Jurnal Perkembangan Sikap Sosial oleh Wali Kelas dan Guru BK.docx",
    "size": 4864,
    "name": "Salinan 04. Jurnal Perkembangan Sikap Sosial oleh Wali Kelas dan Guru BK.docx"
  },
  {
    "path": "Format lampiran penilaian/Salinan 05. Jurnal Perkembangan Sikap Spiritual  (Observasi Tebuka).docx",
    "size": 4506,
    "name": "Salinan 05. Jurnal Perkembangan Sikap Spiritual  (Observasi Tebuka).docx"
  },
  {
    "path": "Format lampiran penilaian/Salinan 06. Jurnal Perkembangan Sikap Spiritual  (Observasi Tertutup).docx",
    "size": 4625,
    "name": "Salinan 06. Jurnal Perkembangan Sikap Spiritual  (Observasi Tertutup).docx"
  },
  {
    "path": "Format lampiran penilaian/Salinan 07. Jurnal Perkembangan Sikap Spiritual dan Sosial oleh Wali Kelas dan Guru BK.docx",
    "size": 4706,
    "name": "Salinan 07. Jurnal Perkembangan Sikap Spiritual dan Sosial oleh Wali Kelas dan Guru BK.docx"
  },
  {
    "path": "Format lampiran penilaian/Salinan 08. Jurnal Perkembangan Sikap Spiritual oleh Wali Kelas dan Guru BK.docx",
    "size": 4731,
    "name": "Salinan 08. Jurnal Perkembangan Sikap Spiritual oleh Wali Kelas dan Guru BK.docx"
  },
  {
    "path": "Format lampiran penilaian/Salinan 09. Jurnal Sikap Spiritual dan Sosial oleh Pendidik.docx",
    "size": 4601,
    "name": "Salinan 09. Jurnal Sikap Spiritual dan Sosial oleh Pendidik.docx"
  },
  {
    "path": "Format lampiran penilaian/Salinan 10. Kisi-kisi Penilaian Praktik Diskusi.docx",
    "size": 9181,
    "name": "Salinan 10. Kisi-kisi Penilaian Praktik Diskusi.docx"
  },
  {
    "path": "Format lampiran penilaian/Salinan 11. Kisi-kisi Penilaian Praktik.docx",
    "size": 9356,
    "name": "Salinan 11. Kisi-kisi Penilaian Praktik.docx"
  },
  {
    "path": "Format lampiran penilaian/Salinan 12. Kisi-kisi Penilaian Produk.docx",
    "size": 7025,
    "name": "Salinan 12. Kisi-kisi Penilaian Produk.docx"
  },
  {
    "path": "Format lampiran penilaian/Salinan 13. Kisi-Kisi Penilaian Proyek.docx",
    "size": 8312,
    "name": "Salinan 13. Kisi-Kisi Penilaian Proyek.docx"
  },
  {
    "path": "Format lampiran penilaian/Salinan 14. Kisi-Kisi Tugas.docx",
    "size": 6774,
    "name": "Salinan 14. Kisi-Kisi Tugas.docx"
  },
  {
    "path": "Format lampiran penilaian/Salinan 15. Lampiran Portofolio.docx",
    "size": 10023,
    "name": "Salinan 15. Lampiran Portofolio.docx"
  },
  {
    "path": "Format lampiran penilaian/Salinan 16. Lembar Penilaian Diri Peserta didik dengan Dua Jawaban.docx",
    "size": 4635,
    "name": "Salinan 16. Lembar Penilaian Diri Peserta didik dengan Dua Jawaban.docx"
  },
  {
    "path": "Format lampiran penilaian/Salinan 17. Lembar Penilaian Diri Peserta didik dengan Empat Jawaban.docx",
    "size": 4728,
    "name": "Salinan 17. Lembar Penilaian Diri Peserta didik dengan Empat Jawaban.docx"
  },
  {
    "path": "Format lampiran penilaian/Salinan 18. Tes Tertulis.docx",
    "size": 7603,
    "name": "Salinan 18. Tes Tertulis.docx"
  },
  {
    "path": "PAI KELAS 1/ANALISA ALOKASI WAKTU/analisa alokasi waktu.docx",
    "size": 18568,
    "name": "analisa alokasi waktu.docx"
  },
  {
    "path": "PAI KELAS 1/ATP/ATP_PAI_KLS 1.docx",
    "size": 4623690,
    "name": "ATP_PAI_KLS 1.docx"
  },
  {
    "path": "PAI KELAS 1/CP/CP_PAI_KLS 1.docx",
    "size": 4620694,
    "name": "CP_PAI_KLS 1.docx"
  },
  {
    "path": "PAI KELAS 1/JURNAL MENGAJAR HRIAN/Jurnal Mengajar_PAI_KLS 1.docx",
    "size": 4071592,
    "name": "Jurnal Mengajar_PAI_KLS 1.docx"
  },
  {
    "path": "PAI KELAS 1/KKTP/KKTP_PAI_KLS 1.docx",
    "size": 4071091,
    "name": "KKTP_PAI_KLS 1.docx"
  },
  {
    "path": "PAI KELAS 1/LKPD/LKPD_PAI_BAB 1.docx",
    "size": 6420056,
    "name": "LKPD_PAI_BAB 1.docx"
  },
  {
    "path": "PAI KELAS 1/LKPD/LKPD_PAI_BAB 10.docx",
    "size": 4838014,
    "name": "LKPD_PAI_BAB 10.docx"
  },
  {
    "path": "PAI KELAS 1/LKPD/LKPD_PAI_BAB 2.docx",
    "size": 4837992,
    "name": "LKPD_PAI_BAB 2.docx"
  },
  {
    "path": "PAI KELAS 1/LKPD/LKPD_PAI_BAB 3.docx",
    "size": 5661956,
    "name": "LKPD_PAI_BAB 3.docx"
  },
  {
    "path": "PAI KELAS 1/LKPD/LKPD_PAI_BAB 4.docx",
    "size": 5094350,
    "name": "LKPD_PAI_BAB 4.docx"
  },
  {
    "path": "PAI KELAS 1/LKPD/LKPD_PAI_BAB 5.docx",
    "size": 4837197,
    "name": "LKPD_PAI_BAB 5.docx"
  },
  {
    "path": "PAI KELAS 1/LKPD/LKPD_PAI_BAB 6.docx",
    "size": 5662690,
    "name": "LKPD_PAI_BAB 6.docx"
  },
  {
    "path": "PAI KELAS 1/LKPD/LKPD_PAI_BAB 7.docx",
    "size": 4837258,
    "name": "LKPD_PAI_BAB 7.docx"
  },
  {
    "path": "PAI KELAS 1/LKPD/LKPD_PAI_BAB 9.docx",
    "size": 4837164,
    "name": "LKPD_PAI_BAB 9.docx"
  },
  {
    "path": "PAI KELAS 1/MODUL AJAR/KLS 1_PAI_BAB 1.docx",
    "size": 5149960,
    "name": "KLS 1_PAI_BAB 1.docx"
  },
  {
    "path": "PAI KELAS 1/MODUL AJAR/KLS 1_PAI_BAB 10.docx",
    "size": 5138342,
    "name": "KLS 1_PAI_BAB 10.docx"
  },
  {
    "path": "PAI KELAS 1/MODUL AJAR/KLS 1_PAI_BAB 2.docx",
    "size": 5145449,
    "name": "KLS 1_PAI_BAB 2.docx"
  },
  {
    "path": "PAI KELAS 1/MODUL AJAR/KLS 1_PAI_BAB 3.docx",
    "size": 5138068,
    "name": "KLS 1_PAI_BAB 3.docx"
  },
  {
    "path": "PAI KELAS 1/MODUL AJAR/KLS 1_PAI_BAB 4.docx",
    "size": 5145362,
    "name": "KLS 1_PAI_BAB 4.docx"
  },
  {
    "path": "PAI KELAS 1/MODUL AJAR/KLS 1_PAI_BAB 5.docx",
    "size": 4591762,
    "name": "KLS 1_PAI_BAB 5.docx"
  },
  {
    "path": "PAI KELAS 1/MODUL AJAR/KLS 1_PAI_BAB 6.docx",
    "size": 4589443,
    "name": "KLS 1_PAI_BAB 6.docx"
  },
  {
    "path": "PAI KELAS 1/MODUL AJAR/KLS 1_PAI_BAB 7.docx",
    "size": 5143729,
    "name": "KLS 1_PAI_BAB 7.docx"
  },
  {
    "path": "PAI KELAS 1/MODUL AJAR/KLS 1_PAI_BAB 8.docx",
    "size": 5144979,
    "name": "KLS 1_PAI_BAB 8.docx"
  },
  {
    "path": "PAI KELAS 1/MODUL AJAR/KLS 1_PAI_BAB 9.docx",
    "size": 4592358,
    "name": "KLS 1_PAI_BAB 9.docx"
  },
  {
    "path": "PAI KELAS 1/PROSEM/PROSEM_PAI_KLS 1.docx",
    "size": 4069988,
    "name": "PROSEM_PAI_KLS 1.docx"
  },
  {
    "path": "PAI KELAS 1/PROTA/PROTA_PAI_KLS 1.docx",
    "size": 4067746,
    "name": "PROTA_PAI_KLS 1.docx"
  },
  {
    "path": "PAI KELAS 2/ANALISA ALOKASI WAKTU/ANALISA ALOKASI WAKTU.docx",
    "size": 18868,
    "name": "ANALISA ALOKASI WAKTU.docx"
  },
  {
    "path": "PAI KELAS 2/ATP/ALUR TUJUAN PEMBELAJARAN (ATP).docx",
    "size": 4272686,
    "name": "ALUR TUJUAN PEMBELAJARAN (ATP).docx"
  },
  {
    "path": "PAI KELAS 2/CP/CAPAIAN PEMBELAJARAN (CP).docx",
    "size": 4271578,
    "name": "CAPAIAN PEMBELAJARAN (CP).docx"
  },
  {
    "path": "PAI KELAS 2/Islam-BG-KLS-II.pdf",
    "size": 2364840,
    "name": "Islam-BG-KLS-II.pdf"
  },
  {
    "path": "PAI KELAS 2/JURNAL MEENGAJAR HARIAN/JURNAL MENGAJAR HARIAN.docx",
    "size": 4624310,
    "name": "JURNAL MENGAJAR HARIAN.docx"
  },
  {
    "path": "PAI KELAS 2/KKTP/.DS_Store",
    "size": 6148,
    "name": ".DS_Store"
  },
  {
    "path": "PAI KELAS 2/KKTP/KRITERIA KETERCAPAIAN TUJUAN PEMBELAJARAN (KKTP).docx",
    "size": 5100194,
    "name": "KRITERIA KETERCAPAIAN TUJUAN PEMBELAJARAN (KKTP).docx"
  },
  {
    "path": "PAI KELAS 2/LKPD/LKPD BAB 1.docx",
    "size": 5595354,
    "name": "LKPD BAB 1.docx"
  },
  {
    "path": "PAI KELAS 2/LKPD/LKPD BAB 10.docx",
    "size": 4272602,
    "name": "LKPD BAB 10.docx"
  },
  {
    "path": "PAI KELAS 2/LKPD/LKPD BAB 2.docx",
    "size": 7281591,
    "name": "LKPD BAB 2.docx"
  },
  {
    "path": "PAI KELAS 2/LKPD/LKPD BAB 3.docx",
    "size": 5595308,
    "name": "LKPD BAB 3.docx"
  },
  {
    "path": "PAI KELAS 2/LKPD/LKPD BAB 4.docx",
    "size": 5596023,
    "name": "LKPD BAB 4.docx"
  },
  {
    "path": "PAI KELAS 2/LKPD/LKPD BAB 5.docx",
    "size": 4271772,
    "name": "LKPD BAB 5.docx"
  },
  {
    "path": "PAI KELAS 2/LKPD/LKPD BAB 6.docx",
    "size": 5095949,
    "name": "LKPD BAB 6.docx"
  },
  {
    "path": "PAI KELAS 2/LKPD/LKPD BAB 7.docx",
    "size": 6918921,
    "name": "LKPD BAB 7.docx"
  },
  {
    "path": "PAI KELAS 2/LKPD/LKPD BAB 8.docx",
    "size": 6918559,
    "name": "LKPD BAB 8.docx"
  },
  {
    "path": "PAI KELAS 2/LKPD/LKPD BAB 9.docx",
    "size": 5594376,
    "name": "LKPD BAB 9.docx"
  },
  {
    "path": "PAI KELAS 2/MODUL AJAR/PAI KELAS 2 BAB 1.docx",
    "size": 21141,
    "name": "PAI KELAS 2 BAB 1.docx"
  },
  {
    "path": "PAI KELAS 2/MODUL AJAR/PAI KELAS 2 BAB 10.docx",
    "size": 4587117,
    "name": "PAI KELAS 2 BAB 10.docx"
  },
  {
    "path": "PAI KELAS 2/MODUL AJAR/PAI KELAS 2 BAB 2.docx",
    "size": 5145992,
    "name": "PAI KELAS 2 BAB 2.docx"
  },
  {
    "path": "PAI KELAS 2/MODUL AJAR/PAI KELAS 2 BAB 3.docx",
    "size": 5145978,
    "name": "PAI KELAS 2 BAB 3.docx"
  },
  {
    "path": "PAI KELAS 2/MODUL AJAR/PAI KELAS 2 BAB 4.docx",
    "size": 5145986,
    "name": "PAI KELAS 2 BAB 4.docx"
  },
  {
    "path": "PAI KELAS 2/MODUL AJAR/PAI KELAS 2 BAB 5.docx",
    "size": 5140365,
    "name": "PAI KELAS 2 BAB 5.docx"
  },
  {
    "path": "PAI KELAS 2/MODUL AJAR/PAI KELAS 2 BAB 6.docx",
    "size": 5140211,
    "name": "PAI KELAS 2 BAB 6.docx"
  },
  {
    "path": "PAI KELAS 2/MODUL AJAR/PAI KELAS 2 BAB 7.docx",
    "size": 5138956,
    "name": "PAI KELAS 2 BAB 7.docx"
  },
  {
    "path": "PAI KELAS 2/MODUL AJAR/PAI KELAS 2 BAB 8.docx",
    "size": 5139544,
    "name": "PAI KELAS 2 BAB 8.docx"
  },
  {
    "path": "PAI KELAS 2/MODUL AJAR/PAI KELAS 2 BAB 9.docx",
    "size": 5138445,
    "name": "PAI KELAS 2 BAB 9.docx"
  },
  {
    "path": "PAI KELAS 2/PROGRAM SEMESTER/PROGRAM SEMESTER (PROSEM).docx",
    "size": 4272390,
    "name": "PROGRAM SEMESTER (PROSEM).docx"
  },
  {
    "path": "PAI KELAS 2/PROGRAM TAHUNAN/PROGRAM TAHUNAN (PROTA).docx",
    "size": 4270473,
    "name": "PROGRAM TAHUNAN (PROTA).docx"
  },
  {
    "path": "PAI KELAS 3/CP/PAI_3_CP.docx",
    "size": 17472,
    "name": "PAI_3_CP.docx"
  },
  {
    "path": "PAI KELAS 3/JURNAL HARIAN MENGAJAR/JURNAL HARIAN_PAI_3.docx",
    "size": 17628,
    "name": "JURNAL HARIAN_PAI_3.docx"
  },
  {
    "path": "PAI KELAS 3/KKTP/PAI_3_KKTP.docx",
    "size": 19141,
    "name": "PAI_3_KKTP.docx"
  },
  {
    "path": "PAI KELAS 3/LKPD/LKPD_PAI_KELAS 3_BAB 1.docx",
    "size": 19634,
    "name": "LKPD_PAI_KELAS 3_BAB 1.docx"
  },
  {
    "path": "PAI KELAS 3/LKPD/LKPD_PAI_KELAS 3_BAB 10.docx",
    "size": 16421,
    "name": "LKPD_PAI_KELAS 3_BAB 10.docx"
  },
  {
    "path": "PAI KELAS 3/LKPD/LKPD_PAI_KELAS 3_BAB 2.docx",
    "size": 18271,
    "name": "LKPD_PAI_KELAS 3_BAB 2.docx"
  },
  {
    "path": "PAI KELAS 3/LKPD/LKPD_PAI_KELAS 3_BAB 3.docx",
    "size": 19254,
    "name": "LKPD_PAI_KELAS 3_BAB 3.docx"
  },
  {
    "path": "PAI KELAS 3/LKPD/LKPD_PAI_KELAS 3_BAB 4.docx",
    "size": 18742,
    "name": "LKPD_PAI_KELAS 3_BAB 4.docx"
  },
  {
    "path": "PAI KELAS 3/LKPD/LKPD_PAI_KELAS 3_BAB 5.docx",
    "size": 18230,
    "name": "LKPD_PAI_KELAS 3_BAB 5.docx"
  },
  {
    "path": "PAI KELAS 3/LKPD/LKPD_PAI_KELAS 3_BAB 6.docx",
    "size": 18124,
    "name": "LKPD_PAI_KELAS 3_BAB 6.docx"
  },
  {
    "path": "PAI KELAS 3/LKPD/LKPD_PAI_KELAS 3_BAB 7.docx",
    "size": 18538,
    "name": "LKPD_PAI_KELAS 3_BAB 7.docx"
  },
  {
    "path": "PAI KELAS 3/LKPD/LKPD_PAI_KELAS 3_BAB 8.docx",
    "size": 17471,
    "name": "LKPD_PAI_KELAS 3_BAB 8.docx"
  },
  {
    "path": "PAI KELAS 3/LKPD/LKPD_PAI_KELAS 3_BAB 9.docx",
    "size": 17831,
    "name": "LKPD_PAI_KELAS 3_BAB 9.docx"
  },
  {
    "path": "PAI KELAS 3/MODUL AJAR/PAI_3_ATP.docx",
    "size": 19365,
    "name": "PAI_3_ATP.docx"
  },
  {
    "path": "PAI KELAS 3/MODUL AJAR/PAI_3_BAB 1.docx",
    "size": 29608,
    "name": "PAI_3_BAB 1.docx"
  },
  {
    "path": "PAI KELAS 3/MODUL AJAR/PAI_3_BAB 2.docx",
    "size": 27938,
    "name": "PAI_3_BAB 2.docx"
  },
  {
    "path": "PAI KELAS 3/MODUL AJAR/PAI_3_BAB 3.docx",
    "size": 26430,
    "name": "PAI_3_BAB 3.docx"
  },
  {
    "path": "PAI KELAS 3/MODUL AJAR/PAI_3_BAB 4.docx",
    "size": 26351,
    "name": "PAI_3_BAB 4.docx"
  },
  {
    "path": "PAI KELAS 3/MODUL AJAR/PAI_3_BAB 5.docx",
    "size": 26587,
    "name": "PAI_3_BAB 5.docx"
  },
  {
    "path": "PAI KELAS 3/MODUL AJAR/PAI_3_BAB 6.docx",
    "size": 26983,
    "name": "PAI_3_BAB 6.docx"
  },
  {
    "path": "PAI KELAS 3/MODUL AJAR/PAI_3_BAB 7.docx",
    "size": 26338,
    "name": "PAI_3_BAB 7.docx"
  },
  {
    "path": "PAI KELAS 3/MODUL AJAR/PAI_3_BAB10.docx",
    "size": 26294,
    "name": "PAI_3_BAB10.docx"
  },
  {
    "path": "PAI KELAS 3/MODUL AJAR/PAI_3_BAB8.docx",
    "size": 26263,
    "name": "PAI_3_BAB8.docx"
  },
  {
    "path": "PAI KELAS 3/MODUL AJAR/PAI_3_BAB9.docx",
    "size": 26602,
    "name": "PAI_3_BAB9.docx"
  },
  {
    "path": "PAI KELAS 3/PROSEM/PAI_3_PROSEM.docx",
    "size": 18500,
    "name": "PAI_3_PROSEM.docx"
  },
  {
    "path": "PAI KELAS 3/PROTA/PAI_3_Prota.docx",
    "size": 16903,
    "name": "PAI_3_Prota.docx"
  },
  {
    "path": "PAI KELAS 4/ATP/ALUR TUJUAN PEMBELAJARAN (ATP).docx",
    "size": 5097251,
    "name": "ALUR TUJUAN PEMBELAJARAN (ATP).docx"
  },
  {
    "path": "PAI KELAS 4/CP/CAPAIAN PEMBELAJARAN (CP).docx",
    "size": 5093478,
    "name": "CAPAIAN PEMBELAJARAN (CP).docx"
  },
  {
    "path": "PAI KELAS 4/Islam-BG-KLS-IV.pdf",
    "size": 2949357,
    "name": "Islam-BG-KLS-IV.pdf"
  },
  {
    "path": "PAI KELAS 4/JURNAL HARIAN MENGAJAR/JURNAL HARIAN GURU.docx",
    "size": 4269506,
    "name": "JURNAL HARIAN GURU.docx"
  },
  {
    "path": "PAI KELAS 4/KKTP/KRITERIA KETERCAPAIAN TUJUAN PEMBELAJARAN (KKTP).docx",
    "size": 5097328,
    "name": "KRITERIA KETERCAPAIAN TUJUAN PEMBELAJARAN (KKTP).docx"
  },
  {
    "path": "PAI KELAS 4/LKPD/LKPD BAB 1.docx",
    "size": 6453969,
    "name": "LKPD BAB 1.docx"
  },
  {
    "path": "PAI KELAS 4/LKPD/LKPD BAB 10.docx",
    "size": 4271289,
    "name": "LKPD BAB 10.docx"
  },
  {
    "path": "PAI KELAS 4/LKPD/LKPD BAB 2.docx",
    "size": 4271678,
    "name": "LKPD BAB 2.docx"
  },
  {
    "path": "PAI KELAS 4/LKPD/LKPD BAB 3.docx",
    "size": 5095390,
    "name": "LKPD BAB 3.docx"
  },
  {
    "path": "PAI KELAS 4/LKPD/LKPD BAB 4.docx",
    "size": 4272398,
    "name": "LKPD BAB 4.docx"
  },
  {
    "path": "PAI KELAS 4/LKPD/LKPD BAB 5.docx",
    "size": 4271497,
    "name": "LKPD BAB 5.docx"
  },
  {
    "path": "PAI KELAS 4/LKPD/LKPD BAB 6.docx",
    "size": 5095102,
    "name": "LKPD BAB 6.docx"
  },
  {
    "path": "PAI KELAS 4/LKPD/LKPD BAB 7.docx",
    "size": 4269729,
    "name": "LKPD BAB 7.docx"
  },
  {
    "path": "PAI KELAS 4/LKPD/LKPD BAB 8.docx",
    "size": 5958483,
    "name": "LKPD BAB 8.docx"
  },
  {
    "path": "PAI KELAS 4/LKPD/LKPD BAB 9.docx",
    "size": 5628863,
    "name": "LKPD BAB 9.docx"
  },
  {
    "path": "PAI KELAS 4/MODUL AJAR/PAI KELAS 4 BAB 1.docx",
    "size": 7336638,
    "name": "PAI KELAS 4 BAB 1.docx"
  },
  {
    "path": "PAI KELAS 4/MODUL AJAR/PAI KELAS 4 BAB 10.docx",
    "size": 7333611,
    "name": "PAI KELAS 4 BAB 10.docx"
  },
  {
    "path": "PAI KELAS 4/MODUL AJAR/PAI KELAS 4 BAB 2.docx",
    "size": 7325761,
    "name": "PAI KELAS 4 BAB 2.docx"
  },
  {
    "path": "PAI KELAS 4/MODUL AJAR/PAI KELAS 4 BAB 3.docx",
    "size": 7333236,
    "name": "PAI KELAS 4 BAB 3.docx"
  },
  {
    "path": "PAI KELAS 4/MODUL AJAR/PAI KELAS 4 BAB 4.docx",
    "size": 7333877,
    "name": "PAI KELAS 4 BAB 4.docx"
  },
  {
    "path": "PAI KELAS 4/MODUL AJAR/PAI KELAS 4 BAB 5.docx",
    "size": 7333823,
    "name": "PAI KELAS 4 BAB 5.docx"
  },
  {
    "path": "PAI KELAS 4/MODUL AJAR/PAI KELAS 4 BAB 6.docx",
    "size": 7334802,
    "name": "PAI KELAS 4 BAB 6.docx"
  },
  {
    "path": "PAI KELAS 4/MODUL AJAR/PAI KELAS 4 BAB 7.docx",
    "size": 7332228,
    "name": "PAI KELAS 4 BAB 7.docx"
  },
  {
    "path": "PAI KELAS 4/MODUL AJAR/PAI KELAS 4 BAB 8.docx",
    "size": 7333104,
    "name": "PAI KELAS 4 BAB 8.docx"
  },
  {
    "path": "PAI KELAS 4/MODUL AJAR/PAI KELAS 4 BAB 9.docx",
    "size": 7332637,
    "name": "PAI KELAS 4 BAB 9.docx"
  },
  {
    "path": "PAI KELAS 4/PROSEM/PROGRAM SEMESTER (PROSEM).docx",
    "size": 5136709,
    "name": "PROGRAM SEMESTER (PROSEM).docx"
  },
  {
    "path": "PAI KELAS 4/PROTA/PROGRAM TAHUNAN (PROTA).docx",
    "size": 5960394,
    "name": "PROGRAM TAHUNAN (PROTA).docx"
  },
  {
    "path": "PAI KELAS 5/ATP/ATP_PAI_5.docx",
    "size": 4273334,
    "name": "ATP_PAI_5.docx"
  },
  {
    "path": "PAI KELAS 5/CP/CP_PAI_5.docx",
    "size": 5097144,
    "name": "CP_PAI_5.docx"
  },
  {
    "path": "PAI KELAS 5/JURNAL MENGAJAR HARIAN/Jurnal_PAI_5.docx",
    "size": 5107056,
    "name": "Jurnal_PAI_5.docx"
  },
  {
    "path": "PAI KELAS 5/KKTP/KKTP_PAI_5.docx",
    "size": 5099486,
    "name": "KKTP_PAI_5.docx"
  },
  {
    "path": "PAI KELAS 5/LKPD/LKPD_PAI_5_BAB 1.docx",
    "size": 4273892,
    "name": "LKPD_PAI_5_BAB 1.docx"
  },
  {
    "path": "PAI KELAS 5/LKPD/LKPD_PAI_5_BAB 10.docx",
    "size": 4271899,
    "name": "LKPD_PAI_5_BAB 10.docx"
  },
  {
    "path": "PAI KELAS 5/LKPD/LKPD_PAI_5_BAB 2.docx",
    "size": 4272123,
    "name": "LKPD_PAI_5_BAB 2.docx"
  },
  {
    "path": "PAI KELAS 5/LKPD/LKPD_PAI_5_BAB 3.docx",
    "size": 4272235,
    "name": "LKPD_PAI_5_BAB 3.docx"
  },
  {
    "path": "PAI KELAS 5/LKPD/LKPD_PAI_5_BAB 4.docx",
    "size": 4271566,
    "name": "LKPD_PAI_5_BAB 4.docx"
  },
  {
    "path": "PAI KELAS 5/LKPD/LKPD_PAI_5_BAB 5.docx",
    "size": 4272026,
    "name": "LKPD_PAI_5_BAB 5.docx"
  },
  {
    "path": "PAI KELAS 5/LKPD/LKPD_PAI_5_BAB 6.docx",
    "size": 6420287,
    "name": "LKPD_PAI_5_BAB 6.docx"
  },
  {
    "path": "PAI KELAS 5/LKPD/LKPD_PAI_5_BAB 7.docx",
    "size": 5097148,
    "name": "LKPD_PAI_5_BAB 7.docx"
  },
  {
    "path": "PAI KELAS 5/LKPD/LKPD_PAI_5_BAB 8.docx",
    "size": 5096491,
    "name": "LKPD_PAI_5_BAB 8.docx"
  },
  {
    "path": "PAI KELAS 5/LKPD/LKPD_PAI_5_BAB 9.docx",
    "size": 4272579,
    "name": "LKPD_PAI_5_BAB 9.docx"
  },
  {
    "path": "PAI KELAS 5/MODUL AJAR/PAI_5_BAB 1.docx",
    "size": 5977756,
    "name": "PAI_5_BAB 1.docx"
  },
  {
    "path": "PAI KELAS 5/MODUL AJAR/PAI_5_BAB 10.docx",
    "size": 5970804,
    "name": "PAI_5_BAB 10.docx"
  },
  {
    "path": "PAI KELAS 5/MODUL AJAR/PAI_5_BAB 2.docx",
    "size": 5972403,
    "name": "PAI_5_BAB 2.docx"
  },
  {
    "path": "PAI KELAS 5/MODUL AJAR/PAI_5_BAB 3.docx",
    "size": 5972558,
    "name": "PAI_5_BAB 3.docx"
  },
  {
    "path": "PAI KELAS 5/MODUL AJAR/PAI_5_BAB 4.docx",
    "size": 5973687,
    "name": "PAI_5_BAB 4.docx"
  },
  {
    "path": "PAI KELAS 5/MODUL AJAR/PAI_5_BAB 5.docx",
    "size": 1964546,
    "name": "PAI_5_BAB 5.docx"
  },
  {
    "path": "PAI KELAS 5/MODUL AJAR/PAI_5_BAB 6.docx",
    "size": 1964139,
    "name": "PAI_5_BAB 6.docx"
  },
  {
    "path": "PAI KELAS 5/MODUL AJAR/PAI_5_BAB 7.docx",
    "size": 5972297,
    "name": "PAI_5_BAB 7.docx"
  },
  {
    "path": "PAI KELAS 5/MODUL AJAR/PAI_5_BAB 8.docx",
    "size": 5970907,
    "name": "PAI_5_BAB 8.docx"
  },
  {
    "path": "PAI KELAS 5/MODUL AJAR/PAI_5_BAB 9.docx",
    "size": 5971016,
    "name": "PAI_5_BAB 9.docx"
  },
  {
    "path": "PAI KELAS 5/PROSEM/PROSEM_PAI_5.docx",
    "size": 4275256,
    "name": "PROSEM_PAI_5.docx"
  },
  {
    "path": "PAI KELAS 5/PROTA/PROTA_PAI_5.docx",
    "size": 4270180,
    "name": "PROTA_PAI_5.docx"
  },
  {
    "path": "PAI KELAS 6/ATP/ALUR TUJUAN PEMBELAJARAN (ATP).docx",
    "size": 19128,
    "name": "ALUR TUJUAN PEMBELAJARAN (ATP).docx"
  },
  {
    "path": "PAI KELAS 6/CP/CAPAIAN PEMBELAJARAN (CP).docx",
    "size": 18554,
    "name": "CAPAIAN PEMBELAJARAN (CP).docx"
  },
  {
    "path": "PAI KELAS 6/Islam_BG_KLS_VI.pdf",
    "size": 2339298,
    "name": "Islam_BG_KLS_VI.pdf"
  },
  {
    "path": "PAI KELAS 6/Jurnal/JURNAL PEMBELAJARAN HARIAN.docx",
    "size": 17342,
    "name": "JURNAL PEMBELAJARAN HARIAN.docx"
  },
  {
    "path": "PAI KELAS 6/kktp/KRITERIA KETERCAPAIAN TUJUAN PEMBELAJARAN (KKTP).docx",
    "size": 18861,
    "name": "KRITERIA KETERCAPAIAN TUJUAN PEMBELAJARAN (KKTP).docx"
  },
  {
    "path": "PAI KELAS 6/LKPD/LKPD BAB 1.docx",
    "size": 18967,
    "name": "LKPD BAB 1.docx"
  },
  {
    "path": "PAI KELAS 6/LKPD/LKPD BAB 10.docx",
    "size": 18915,
    "name": "LKPD BAB 10.docx"
  },
  {
    "path": "PAI KELAS 6/LKPD/LKPD BAB 2.docx",
    "size": 19032,
    "name": "LKPD BAB 2.docx"
  },
  {
    "path": "PAI KELAS 6/LKPD/LKPD BAB 3.docx",
    "size": 18388,
    "name": "LKPD BAB 3.docx"
  },
  {
    "path": "PAI KELAS 6/LKPD/LKPD BAB 4.docx",
    "size": 18488,
    "name": "LKPD BAB 4.docx"
  },
  {
    "path": "PAI KELAS 6/LKPD/LKPD BAB 5.docx",
    "size": 18791,
    "name": "LKPD BAB 5.docx"
  },
  {
    "path": "PAI KELAS 6/LKPD/LKPD BAB 6.docx",
    "size": 18566,
    "name": "LKPD BAB 6.docx"
  },
  {
    "path": "PAI KELAS 6/LKPD/LKPD BAB 7.docx",
    "size": 19838,
    "name": "LKPD BAB 7.docx"
  },
  {
    "path": "PAI KELAS 6/LKPD/LKPD BAB 8.docx",
    "size": 19215,
    "name": "LKPD BAB 8.docx"
  },
  {
    "path": "PAI KELAS 6/LKPD/LKPD BAB 9.docx",
    "size": 19164,
    "name": "LKPD BAB 9.docx"
  },
  {
    "path": "PAI KELAS 6/Modul/PAI KELAS 6 BAB 1.docx",
    "size": 5967592,
    "name": "PAI KELAS 6 BAB 1.docx"
  },
  {
    "path": "PAI KELAS 6/Modul/PAI KELAS 6 BAB 10.docx",
    "size": 5140015,
    "name": "PAI KELAS 6 BAB 10.docx"
  },
  {
    "path": "PAI KELAS 6/Modul/PAI KELAS 6 BAB 2.docx",
    "size": 5139855,
    "name": "PAI KELAS 6 BAB 2.docx"
  },
  {
    "path": "PAI KELAS 6/Modul/PAI KELAS 6 BAB 3.docx",
    "size": 5964675,
    "name": "PAI KELAS 6 BAB 3.docx"
  },
  {
    "path": "PAI KELAS 6/Modul/PAI KELAS 6 BAB 4.docx",
    "size": 5140695,
    "name": "PAI KELAS 6 BAB 4.docx"
  },
  {
    "path": "PAI KELAS 6/Modul/PAI KELAS 6 BAB 5.docx",
    "size": 5964907,
    "name": "PAI KELAS 6 BAB 5.docx"
  },
  {
    "path": "PAI KELAS 6/Modul/PAI KELAS 6 BAB 6.docx",
    "size": 5964501,
    "name": "PAI KELAS 6 BAB 6.docx"
  },
  {
    "path": "PAI KELAS 6/Modul/PAI KELAS 6 BAB 7.docx",
    "size": 5140483,
    "name": "PAI KELAS 6 BAB 7.docx"
  },
  {
    "path": "PAI KELAS 6/Modul/PAI KELAS 6 BAB 8.docx",
    "size": 5139979,
    "name": "PAI KELAS 6 BAB 8.docx"
  },
  {
    "path": "PAI KELAS 6/Modul/PAI KELAS 6 BAB 9.docx",
    "size": 5139751,
    "name": "PAI KELAS 6 BAB 9.docx"
  },
  {
    "path": "PAI KELAS 6/Prosem/PROGRAM SEMESTER (PROSEM).docx",
    "size": 17852,
    "name": "PROGRAM SEMESTER (PROSEM).docx"
  },
  {
    "path": "PAI KELAS 6/Prota/PROGRAM TAHUNAN (PROTA).docx",
    "size": 16351,
    "name": "PROGRAM TAHUNAN (PROTA).docx"
  }
]